winsystem/Speaker.py
winsystem/Toast.py
winsystem/Volume.py
winsystem/__init__.py
winsystem/helper.py
winsystem/lnk_maker.py
winsystem-1.0.8.dist-info/METADATA
winsystem-1.0.8.dist-info/WHEEL
winsystem-1.0.8.dist-info/top_level.txt
winsystem-1.0.8.dist-info/zip-safe
winsystem-1.0.8.dist-info/RECORD
